treets/__init__.py
treets/_modidx.py
treets/_nbdev.py
treets/core.py
treets-1.0.5.dist-info/LICENSE
treets-1.0.5.dist-info/METADATA
treets-1.0.5.dist-info/WHEEL
treets-1.0.5.dist-info/top_level.txt
treets-1.0.5.dist-info/RECORD
