Metadata-Version: 2.1
Name: treets
Version: 1.0.5
Summary: This library provides functions to analyzes food logging data.
Home-page: https://github.com/FleischerResearchLab/treets/tree/master/
Author: Qiwen Zhang, Jason Fleischer
Author-email: owenzhang1999@gmail.com
License: Apache Software License 2.0
Keywords: circadian ryhthm
Classifier: Development Status :: 3 - Alpha
Classifier: Intended Audience :: Developers
Classifier: Natural Language :: English
Classifier: Programming Language :: Python :: 3.6
Classifier: Programming Language :: Python :: 3.7
Classifier: Programming Language :: Python :: 3.8
Classifier: License :: OSI Approved :: Apache Software License
Requires-Python: >=3.6
License-File: LICENSE
Requires-Dist: pip
Requires-Dist: packaging
Requires-Dist: pandas
Requires-Dist: numpy
Requires-Dist: scipy
Requires-Dist: seaborn
Requires-Dist: matplotlib
Requires-Dist: datetime
Requires-Dist: nltk
Requires-Dist: xlrd
Provides-Extra: dev
